{
  "suggestions": {
    "shouldBePresent": "Should be present",
    "uniqueAcrossPages": "Unique across pages",
    "titleLengthSuggestion": "40-60 characters long",
    "descriptionLengthSuggestion": "140-160 characters long",
    "h1LengthSuggestion": "Below 70 characters",
    "oneH1OnAPage": "1 H1 on a page"
  },
  "tagLengths": {
    "title": {
      "minLength": 25,
      "maxLength": 75,
      "idealMinLength": 40,
      "idealMaxLength": 60
    },
    "description": {
      "minLength": 100,
      "maxLength": 175,
      "idealMinLength": 140,
      "idealMaxLength": 160
    },
    "h1": {
      "maxLength": 75,
      "idealMaxLength": 70
    }
  }
}
